common/__init__.py
common/admin.py
common/apps.py
common/login_urls.py
common/tests.py
common/urls.py
common/helper/__init__.py
common/helper/auth_helper.py
common/helper/basecode_helper.py
common/helper/log_helper.py
common/helper/org_helper.py
common/migrations/0001_initial.py
common/migrations/0002_cmcodedetail_cmcodemaster.py
common/migrations/__init__.py
common/models/__init__.py
common/models/authentication.py
common/models/basecode.py
common/models/corporation.py
common/models/employee.py
common/models/file_template.py
common/models/log.py
common/models/program_menu.py
common/models/sequence.py
common/models/test_models.py
common/models/user_group.py
common/serializers/__init__.py
common/serializers/authentication.py
common/serializers/basecode.py
common/serializers/corporation.py
common/serializers/employee.py
common/serializers/login.py
common/serializers/program_menu.py
common/serializers/test_serializers.py
common/serializers/user_group.py
common/utils/__init__.py
common/views/__init__.py
common/views/authentication.py
common/views/basecode.py
common/views/corporation.py
common/views/dashboard.py
common/views/employee.py
common/views/login.py
common/views/program_menu.py
common/views/search_account.py
common/views/sequence.py
common/views/test_views.py
common/views/user_group.py
vntg_common_test-0.2.dist-info/LICENSE
vntg_common_test-0.2.dist-info/METADATA
vntg_common_test-0.2.dist-info/WHEEL
vntg_common_test-0.2.dist-info/top_level.txt
vntg_common_test-0.2.dist-info/RECORD
